wagtailextras/__init__.py
wagtailextras/blocks.py
wagtailextras/mixins.py
wagtailextras/tests.py
wagtailextras/__pycache__/__init__.cpython-35.pyc
wagtailextras/__pycache__/blocks.cpython-35.pyc
wagtailextras/templates/wagtailextras/empty_block.html
wagtailextras/tests/__init__.py
wagtailextras/tests/models.py
wagtailextras/tests/myests.py
wagtailextras/tests/tests.py
wagtailextras-0.1.3.dist-info/DESCRIPTION.rst
wagtailextras-0.1.3.dist-info/METADATA
wagtailextras-0.1.3.dist-info/RECORD
wagtailextras-0.1.3.dist-info/WHEEL
wagtailextras-0.1.3.dist-info/metadata.json
wagtailextras-0.1.3.dist-info/top_level.txt
