Metadata-Version: 2.0
Name: wagtailextras
Version: 0.1.3
Summary: A bunch of little Wagtail helpers
Home-page: https://github.com/sinnwerkstatt/wagtailextras
Author: Andreas Nüßlein
Author-email: andreas.nuesslein@sinnwerkstatt.com
License: LGPL
Keywords: wagtail
Platform: UNKNOWN
Classifier: Development Status :: 3 - Alpha
Classifier: License :: OSI Approved
Classifier: Intended Audience :: Developers
Classifier: Programming Language :: Python
Classifier: Programming Language :: Python :: 3
Requires-Dist: wagtail
